README.md
setup.py
RusPhonetic/__init__.py
RusPhonetic/phonetic_module.py
RusPhonetic.egg-info/PKG-INFO
RusPhonetic.egg-info/SOURCES.txt
RusPhonetic.egg-info/dependency_links.txt
RusPhonetic.egg-info/top_level.txt