Metadata-Version: 1.2
Name: RusPhonetic
Version: 1.1.0
Summary: Phonetic analysis of the words of the Russian language.
Home-page: https://github.com/NyashniyVladya/RusPhonetic
Author: Vladya
License: UNKNOWN
Keywords: vladya rus russian phonetic
Platform: UNKNOWN
Classifier: Natural Language :: Russian
Classifier: Programming Language :: Python :: 3
Classifier: Programming Language :: Python :: 3.0
Classifier: Programming Language :: Python :: 3.1
Classifier: Programming Language :: Python :: 3.2
Classifier: Programming Language :: Python :: 3.3
Classifier: Programming Language :: Python :: 3.4
Classifier: Programming Language :: Python :: 3.5
Classifier: Programming Language :: Python :: 3.6
Classifier: Programming Language :: Python :: 3.7
Classifier: License :: OSI Approved :: GNU General Public License v3 (GPLv3)
Requires-Python: >=3
